README.md
setup.py
sqlcell/__init__.py
sqlcell/_initdb.py
sqlcell/args.py
sqlcell/db.py
sqlcell/hooks.py
sqlcell/sqlcell.py
sqlcell.egg-info/PKG-INFO
sqlcell.egg-info/SOURCES.txt
sqlcell.egg-info/dependency_links.txt
sqlcell.egg-info/requires.txt
sqlcell.egg-info/top_level.txt