Metadata-Version: 1.1
Name: sqlcell
Version: 0.2.0.15
Summary: run sql in jupyter notebooks or jupyter lab
Home-page: https://github.com/tmthyjames/SQLCell
Author: Tim Dobbins
Author-email: noneya@gmail.com
License: MIT
Platform: UNKNOWN
Classifier: Programming Language :: Python
Classifier: Programming Language :: Python :: 3.6
